Metadata-Version: 2.1
Name: zalupa
Version: 0.0
Summary: zalupa
Home-page: UNKNOWN
Author-email: oleksiy.saurin@gmail.com
License: UNKNOWN
Platform: UNKNOWN
